{
  "parent": "minecraft:recipes/root",
  "criteria": {
    "has_the_recipe": {
      "conditions": {
        "recipe": "geomancyadditions:prismarine_bricks_wall"
      },
      "trigger": "minecraft:recipe_unlocked"
    },
    "prismarine_bricks": {
      "conditions": {
        "items": [
          {
            "items": [
              "minecraft:prismarine_bricks"
            ]
          }
        ]
      },
      "trigger": "minecraft:inventory_changed"
    }
  },
  "requirements": [
    [
      "prismarine_bricks",
      "has_the_recipe"
    ]
  ],
  "rewards": {
    "recipes": [
      "geomancyadditions:prismarine_bricks_wall"
    ]
  }
}