{
  "type": "geomancy:dipping",
  "group": "geomancy",
  "ingredients": [
    {
      "tag": "forge:gems/quartz"
    },
    {
      "item": "minecraft:redstone"
    },
    {
      "item": "minecraft:yellow_dye"
    },
    {
      "item": "minecraft:basalt"
    },
    {
      "item": "minecraft:bamboo"
    },
    {
      "item": "minecraft:bamboo"
    },
    {
      "item": "minecraft:bamboo"
    },
    {
      "item": "minecraft:basalt"
    },
    {
      "item": "minecraft:yellow_dye"
    },
    {
      "item": "minecraft:redstone"
    },
    {
      "item": "minecraft:basalt"
    },
    {
      "item": "minecraft:bamboo"
    },
    {
      "item": "minecraft:basalt"
    },
    {
      "item": "minecraft:redstone"
    },
    {
      "item": "minecraft:yellow_dye"
    }
  ],
  "fluid": {
    "tag": "geomancy:dipping_fluids",
    "amount": 1000
  },
  "output": {
    "item": "geomancy:topaz"
  }
}